{"parse":{"title":"Furniture sets","pageid":1370,"wikitext":{"*":"'''Furniture sets''' are groups of [[furniture]] items that share a common theme and are similar in appearance to one another. The Calamity Mod introduces 22 new sets of furniture.\n\n== Types ==\nThe following table displays the different furniture sets:\n\n{| class=\"terraria lined\" style=\"text-align:center\"\n! Type !! Source !! [[Basin]] !! [[Bathtub]] !! [[Bed]] !! [[Bookcase]] !! [[Candelabra]] !! [[Candle]] !! [[Chair]] !! [[Chandelier]] !! [[Chest]] !! [[Clock]] !! [[Door]] !! [[Dresser]] !! [[Lamp]] !! [[Lantern]] !! [[Piano]] !! [[Platform]] !! [[Sink]] !! [[Sofa]] !! [[Table]] !! [[Toilet]] !! [[Wall]] !! [[Work Bench]] !! [[Crafting station]]\n|-\n| {{/row|type=Abyss|source=Smooth Abyss Gravel|wall=Smooth Abyss Gravel Wall|basin=no|bed=Abyss Bed|candle=Abyss Candle|clock=Abyss Clock|piano=Abyss Synth|platform=Smooth Abyss Gravel Platform|sofa=Abyss Sofa|toilet=no|crafting station=Void Condenser}}\n|-\n| {{/row|type=Acidwood|source=Acidwood|wall=Acidwood Wall|basin=no|bed=Acidwood Bed|candle=Acidwood Candle|clock=Acidwood Clock|piano=Acidwood Piano|platform=Acidwood Platform|sofa=Acidwood Bench|toilet=no|crafting station=no}}\n|-\n| {{/row|type=Ancient|source=Brimstone Slag|wall=Brimstone Slag Wall|basin=Ancient Basin|bed=Ancient Bed|candelabra=no|candle=no|chest=no|clock=Ancient Monolith|piano=Ancient Pipe Organ|platform=no|sofa=Ancient Sofa|toilet=no|crafting station=no}}\n|-\n| {{/row|type=Ancient Navystone|source=Ancient Smooth Navystone|wall=Ancient Smooth Navystone Wall|basin=no|bed=Ancient Navystone Bed|candle=Ancient Navystone Candle|clock=Ancient Navystone Clock|piano=Ancient Navystone Piano|platform=Ancient Navystone Platform|sofa=Ancient Navystone Bench|toilet=no|crafting station=no}}\n|-\n| {{/row|type=Anodized Wulfrum|source=Rounded Anodized Wulfrum Panels|wall=Rounded Anodized Wulfrum Panel Wall|basin=no|bed=Anodized Wulfrum Sleeping Pod|candelabra=no|candle=Anodized Wulfrum Desk Light|chest=Anodized Wulfrum Chest|clock=no|door=Anodized Wulfrum Door|piano=Anodized Wulfrum Jukebox|platform=Anodized Wulfrum Platform|sofa=Anodized Wulfrum Sofa|crafting station=no}}\n|-\n| {{/row|type=Ashen|source=Smooth Brimstone Slag|wall=Smooth Brimstone Slag Wall|basin=Ashen Basin|bed=Ashen Bed|candle=Ashen Candle|clock=Ashen Monolith|piano=Ashen Pipe Organ|platform=Ashen Platform|sofa=Ashen Sofa|toilet=no|crafting station=Ashen Altar}}\n|-\n| {{/row|type=Botanic|source=Uelibloom Brick|wall=Uelibloom Brick Wall|basin=no|bed=Botanic Bed|candle=Botanic Candle|clock=Botanic Clock|piano=Botanic Piano|platform=Botanic Platform|sofa=Botanic Bench|toilet=no|crafting station=no}}\n|-\n| {{/row|type=Cosmilite|source=Cosmilite Brick|wall=Cosmilite Brick Wall|basin=Cosmilite Basin|bed=Cosmilite Bed|candle=Cosmilite Candle|clock=Cosmilite Clock|piano=Cosmilite Piano|platform=Cosmilite Platform|sofa=Cosmilite Sofa|toilet=no|crafting station=no}}\n|-\n| {{/row|type=Driftwood|source=Driftwood|wall=Driftwood Wall|basin=no|bed=Driftwood Bed|candle=Driftwood Candle|clock=Driftwood Sundial|piano=Driftwood Baroque Cello|platform=Driftwood Platform|sofa=Driftwood Sofa|toilet=Driftwood Toilet|crafting station=no}}\n|-\n| {{/row|type=Exo|source=Exo Plating|wall=Exo Plating Wall|basin=no|bed=Exo Bed|candle=Exo Candle|clock=Exo Clock|piano=Exo Keyboard|platform=Exo Platform|sofa=Exo Sofa|crafting station=no}}\n|-\n| {{/row|type=Marnite|source=Polished Marnite Block|wall=Polished Marnite Wall|basin=no|bed=Marnite Bed|candle=Marnite Candle|clock=Marnite Clock|piano=Marnite Organ|platform=Polished Marnite Platform|sofa=Marnite Sofa|toilet=Marnite Toilet|crafting station=no}}\n|-\n| {{/row|type=Monolith|source=Astral Monolith|wall=Astral Monolith Wall|basin=no|bed=Monolith Bed|candle=Monolith Candle|clock=Monolith Clock|piano=Monolith Piano|platform=Monolith Platform|sofa=Monolith Bench|toilet=no|crafting station=no}}\n|-\n| {{/row|type=Navystone|source=Smooth Navystone|wall=Smooth Navystone Wall|basin=no|bed=Navystone Bed|candle=Navystone Candle|clock=Navystone Clock|piano=Navystone Lyre|platform=Navystone Platform|sofa=Navystone Triclinium|toilet=no|crafting station=no}}\n|-\n| {{/row|type=Otherworldly|source=Otherworldly Stone|wall=Otherworldly Stone Wall|basin=no|bed=Otherworldly Bed|candle=Otherworldly Candle|clock=Otherworldly Clock|piano=Otherworldly Piano|platform=Otherworldly Platform|sofa=Otherworldly Sofa|toilet=no|crafting station=no}}\n|-\n| {{/row|type=Plagued|source=Plagued Containment Brick|wall=Plagued Containment Wall|basin=Broken Plagued 'Bed'|bed=Plagued 'Bed'|candle=Plagued Candle|clock=Plagued Clock|piano=Plagued Piano|platform=Plagued Shelf|sofa=Plagued Sofa|toilet=no|crafting station=Plague Infuser}}\n|-\n| {{/row|type=Profaned|source=Profaned Rock|wall=Profaned Rock Wall|basin=Profaned Crucible|bed=Profaned Bed|candle=Profaned Candle|clock=Profaned Clock|piano=Profaned Piano|platform=Profaned Platform|sofa=Profaned Bench|toilet=no|crafting station=Profaned Crucible}}\n|-\n| {{/row|type=Sacrilegious|source=Occult Brick|wall=Occult Brick Wall|basin=no|bed=Sacrilegious Bed|candle=Sacrilegious Candle|clock=Sacrilegious Clock|piano=Sacrilegious Organ|platform=Occult Platform|sofa=Sacrilegious Bench|toilet=no|crafting station=Altar of the Accursed}}\n|-\n| {{/row|type=Silva|source=Silva Crystal|wall=Silva Wall|basin=Silva Basin|bed=Silva Bed|candle=Silva Candle|clock=Silva Clock|piano=Silva Piano|platform=Silva Platform|sofa=Silva Bench|toilet=no|crafting station=no}}\n|-\n| {{/row|type=Statigel|source=Statigel Block|wall=Statigel Wall|basin=no|bed=Statigel Bed|candle=Statigel Candle|clock=Statigel Clock|piano=Statigel Piano|platform=Statigel Platform|sofa=Statigel Sofa|toilet=no|crafting station=no}}\n|-\n| {{/row|type=Stratus|source=Stratus Brick|wall=Stratus Wall|basin=no|bed=Stratus Bed|candle=Stratus Candle|clock=Stratus Clock|piano=Stratus Piano|platform=Stratus Platform|sofa=Stratus Sofa|toilet=no|crafting station=no}}\n|-\n| {{/row|type=Void|source=Smooth Voidstone|wall=Smooth Voidstone Wall|basin=no|bed=Void Bed|candle=Void Candle|clock=Void Obelisk|piano=Void Piano|platform=Smooth Voidstone Platform|sofa=Void Sofa|toilet=no|crafting station=Void Condenser}}\n|-\n| {{/row|type=Wulfrum|source=Wulfrum Plating|wall=Wulfrum Plating Wall|basin=no|bed=Wulfrum Bed|candle=Wulfrum Candle|chest=no|clock=Wulfrum Clock|door=no|piano=Wulfrum Piano|platform=Wulfrum Platform|sofa=Wulfrum Sofa|crafting station=no}}\n|}\n\n=== [[Laboratory furniture]] ===\n{| class=\"terraria lined\" style=\"text-align:center\"\n! Type !! [[Block]] !! [[Chest]] !! Console !! Containment<br/>Box !! Display !! [[Door]] !! Electric<br/>Panel !! Reinforced<br/>Crate !! Screen !! Server !! Terminal !! [[Platform]] !! [[Wall]]\n|-\n| style=\"text-align:left\" | '''Aged Laboratory'''\n| {{item|Rusted Pipes|mode=image}}&nbsp;{{item|Rusted Plating|mode=image}}\n| {{item|Aged Security Chest|mode=image}}\n| {{item|Aged Laboratory Console|mode=image}}\n| {{item|Aged Laboratory Containment Box|mode=image}}\n| {{item|Aged Laboratory Display|mode=image}}\n| {{item|Aged Laboratory Door|mode=image}}\n| {{item|Aged Laboratory Electric Panel|mode=image}}\n| {{item|Aged Reinforced Crate|mode=image}}\n| {{item|Aged Laboratory Screen|mode=image}}\n| {{item|Aged Laboratory Server|mode=image}}\n| {{item|Aged Laboratory Terminal|mode=image}}\n| {{item|Rusted Shelf|mode=image}}\n| {{item|Rusted Plating Wall|mode=image}}\n|-\n| style=\"text-align:left\" | '''Auric'''\n| {{item|Auric Panel|mode=image}}&nbsp;{{item|Exo-Auric Panel|mode=image}}&nbsp;{{item|Auric Absorber|mode=image}}\n| {{no}}\n| {{item|Auric Console|mode=image}}\n| {{no}}\n| {{item|Auric Display|mode=image}}\n| {{no}}\n| {{no}}\n| {{item|Auric Reinforced Crate|mode=image}}\n| {{item|Auric Screen|mode=image}}\n| {{item|Auric Server|mode=image}}\n| {{item|Auric Terminal|mode=image}}\n| {{item|Auric Platform|mode=image}}\n| {{no}}\n|-\n| style=\"text-align:left\" | '''Exo'''\n| {{item|Exo Plating|mode=image}}&nbsp;{{item|Exo Prism Panel|mode=image}}\n| {{item|Exo Chest|mode=image}}\n| {{item|Exo Console|mode=image}}\n| {{no}}\n| {{item|Exo Display|mode=image}}\n| {{item|Exo Door|mode=image}}\n| {{no}}\n| {{no}}\n| {{item|Exo Screen|mode=image}}\n| {{item|Exo Server|mode=image}}\n| {{item|Exo Terminal|mode=image}}\n| {{item|Exo Platform|mode=image}}&nbsp;{{item|Exo Prism Platform|mode=image}}\n| {{item|Exo Plating Wall|mode=image}}&nbsp;{{item|Exo Prism Panel Wall|mode=image}}\n|-\n| style=\"text-align:left\" | '''Laboratory'''\n| {{item|Laboratory Plating|mode=image}}&nbsp;{{item|Laboratory Panels|mode=image}}&nbsp;{{item|Laboratory Pipe Plating|mode=image}}\n| {{item|Security Chest|mode=image}}\n| {{item|Laboratory Console|mode=image}}\n| {{item|Laboratory Containment Box|mode=image}}\n| {{item|Laboratory Display|mode=image}}\n| {{item|Laboratory Door|mode=image}}\n| {{item|Laboratory Electric Panel|mode=image}}\n| {{item|Reinforced Crate|mode=image}}\n| {{item|Laboratory Screen|mode=image}}\n| {{item|Laboratory Server|mode=image}}\n| {{item|Laboratory Terminal|mode=image}}\n| {{item|Laboratory Shelf|mode=image}}\n| {{item|Laboratory Plating Wall|mode=image}}&nbsp;{{item|Laboratory Panel Wall|mode=image}}\n|}\n\n== Partial sets ==\nIn addition to the full sets above, there are some additional types of furniture items that only exist for some sets.\n*'''Banners''': Consists of the {{item|Eye of the Accursed Banner}} and the {{item|Occult Legionnaire Banner}}. Crafted from [[Occult Brick]]s and [[Silk]].\n*'''Monoliths''': Consists of the {{item|Astral Projector}}, crafted from [[Astral Monolith]]; the {{item|Exo Obelisk}}, crafted from [[Exo Plating]]; and the {{item|Monolith of the Accursed}}, crafted from Occult Bricks.\n*'''Ritual Candles''': Consists of the {{item|Large Ritual Candle}} and the {{item|Ritual Candle}}. Crafted from Occult Bricks and [[Torches]].\n*'''Sconces''': Consists of the {{item|Cosmilite Sconce}}, crafted from [[Cosmilite Brick]]s and Torches.\n\n\n== Gallery ==\n<gallery>\nFile:Calamity furniture sets.png|Various furniture sets. Click the image to view each furniture set.\n</gallery>\n\n{{vh}}\n{{Master Template Tiles\n|show-main = yes\n|show-furniture = yes\n}}\n[[Category:Furniture items|*]]\n{{language info|en=Furniture sets}}"}}}